[
  {
    "id": "i3r70dsd23ubiebfi",
    "title" : "No-Rest_for_Dhoni_this-Year",
    "heading": "இந்த வருடம் ஓய்வு இல்லை.. ஆனால்.. கேப்டன் மாற்றம்? இதுதான் சிஎஸ்கே தோனியின் பிளான்? கேப்டன் அவரா?",
    "createdBy": "Raja",
    "createdAt": "2023-05-26T20:21:39.348Z",
    "category": "cricket",
    "bannerImage": {
      "name": "Creicket Image",
      "src": "/images/categories/cricket.jpg"
    },
    "youtubeLink" : "https://youtu.be/tyvnX5_ArB8",
    "images": [
      {
        "src": "https://assets.bcci.tv/bcci/photos/1043/842dee7a-f6b7-4e80-83ff-4fbdfe44eb11.jpg",
        "source": "iplt20.com"
      },
      {
        "src": "https://assets.bcci.tv/bcci/photos/1043/688d01fe-9efb-46ee-b346-41c954812a9a.jpg",
        "source": "iplt20.com"
      },
      {
        "src": "https://assets.bcci.tv/bcci/photos/1043/5cd49266-d531-411b-999a-0c0d0199d949.jpg",
        "source": "iplt20.com"
      },
      {
        "src": "https://assets.bcci.tv/bcci/photos/1043/5cd49266-d531-411b-999a-0c0d0199d949.jpg",
        "source": "iplt20.com"
      },
      {
        "src": "https://assets.bcci.tv/bcci/photos/1043/5cd49266-d531-411b-999a-0c0d0199d949.jpg",
        "source": "iplt20.com"
      },
      {
        "src": "https://assets.bcci.tv/bcci/photos/1043/5cd49266-d531-411b-999a-0c0d0199d949.jpg",
        "source": "iplt20.com"
      }
    ],
    "paragraphs": [
      "இந்த நிலையில்தான் *தோனி* ஐபிஎல் தொடரில் இருந்து ஓய்வு பெற *போவதாக* பேச்சுக்கள் சுற்றி வரும் நிலையில்தான் சிஎஸ்கேவின் அடுத்த கேப்டன் யார் என்பது தொடர்பான ஆலோசனைகள், விவாதங்கள் எழுந்துள்ளன. இந்த நிலையில்தான் தோனி ஐபிஎல் தொடரில் இருந்து ஓய்வு பெற போவதாக பேச்சுக்கள் சுற்றி வரும் நிலையில்தான் சிஎஸ்கேவின் அடுத்த கேப்டன் யார் என்பது தொடர்பான ஆலோசனைகள், விவாதங்கள் எழுந்துள்ளன.",
      "இந்த நிலையில்தான் *தோனி* ஐபிஎல் தொடரில் இருந்து ஓய்வு பெற *போவதாக* பேச்சுக்கள் சுற்றி வரும் நிலையில்தான் சிஎஸ்கேவின் அடுத்த கேப்டன் யார் என்பது தொடர்பான ஆலோசனைகள், விவாதங்கள் எழுந்துள்ளன. இந்த நிலையில்தான் தோனி ஐபிஎல் தொடரில் இருந்து ஓய்வு பெற போவதாக பேச்சுக்கள் சுற்றி வரும் நிலையில்தான் சிஎஸ்கேவின் அடுத்த கேப்டன் யார் என்பது தொடர்பான ஆலோசனைகள், விவாதங்கள் எழுந்துள்ளன.",
      "இந்த நிலையில்தான் *தோனி* ஐபிஎல் தொடரில் இருந்து ஓய்வு பெற *போவதாக* பேச்சுக்கள் சுற்றி வரும் நிலையில்தான் சிஎஸ்கேவின் அடுத்த கேப்டன் யார் என்பது தொடர்பான ஆலோசனைகள், விவாதங்கள் எழுந்துள்ளன. இந்த நிலையில்தான் தோனி ஐபிஎல் தொடரில் இருந்து ஓய்வு பெற போவதாக பேச்சுக்கள் சுற்றி வரும் நிலையில்தான் சிஎஸ்கேவின் அடுத்த கேப்டன் யார் என்பது தொடர்பான ஆலோசனைகள், விவாதங்கள் எழுந்துள்ளன.",
      "இந்த நிலையில்தான் *தோனி* ஐபிஎல் தொடரில் இருந்து ஓய்வு பெற *போவதாக* பேச்சுக்கள் சுற்றி வரும் நிலையில்தான் சிஎஸ்கேவின் அடுத்த கேப்டன் யார் என்பது தொடர்பான ஆலோசனைகள், விவாதங்கள் எழுந்துள்ளன. இந்த நிலையில்தான் தோனி ஐபிஎல் தொடரில் இருந்து ஓய்வு பெற போவதாக பேச்சுக்கள் சுற்றி வரும் நிலையில்தான் சிஎஸ்கேவின் அடுத்த கேப்டன் யார் என்பது தொடர்பான ஆலோசனைகள், விவாதங்கள் எழுந்துள்ளன.",
      "இந்த நிலையில்தான் தோனி ஐபிஎல் தொடரில் இருந்து *ஓய்வு* பெற போவதாக பேச்சுக்கள் சுற்றி வரும் நிலையில்தான் சிஎஸ்கேவின் அடுத்த கேப்டன் யார் என்பது தொடர்பான ஆலோசனைகள், விவாதங்கள் எழுந்துள்ளன. இந்த நிலையில்தான் தோனி ஐபிஎல் தொடரில் இருந்து ஓய்வு பெற போவதாக பேச்சுக்கள் சுற்றி வரும் நிலையில்தான் சிஎஸ்கேவின் அடுத்த கேப்டன் யார் என்பது தொடர்பான ஆலோசனைகள், விவாதங்கள் எழுந்துள்ளன."
    ],
    "tags": ["ipl", "cricket", "csk", "dhoni", "2023"]
  },
  {
    "id": "i3r709r323ubasafi",
    "title" : "This-title-1-is-news",
    "instagramLink":"https://www.instagram.com/p/Cs-h2XNLpE6/?igshid=MmJiY2I4NDBkZg==",

    "heading": "இந்த வருடம் ஓய்வு இல்லை.. ஆனால்.. கேப்டன் மாற்றம்? இதுதான் சிஎஸ்கே தோனியின் பிளான்? கேப்டன் அவரா?",
    "createdBy": "Raja",
    "createdAt": "2023-05-26T20:21:39.348Z",
    "category": "cricket",
    "bannerImage": {
      "name": "Creicket Image",
      "src": "/images/categories/news.jpg"
    },
    "images": [
      {
        "src": "https://assets.bcci.tv/bcci/photos/1043/842dee7a-f6b7-4e80-83ff-4fbdfe44eb11.jpg",
        "source": "iplt20.com"
      },
      {
        "src": "https://assets.bcci.tv/bcci/photos/1043/688d01fe-9efb-46ee-b346-41c954812a9a.jpg",
        "source": "iplt20.com"
      },
      {
        "src": "https://assets.bcci.tv/bcci/photos/1043/5cd49266-d531-411b-999a-0c0d0199d949.jpg",
        "source": "iplt20.com"
      },
      {
        "src": "https://assets.bcci.tv/bcci/photos/1043/5cd49266-d531-411b-999a-0c0d0199d949.jpg",
        "source": "iplt20.com"
      },
      {
        "src": "https://assets.bcci.tv/bcci/photos/1043/5cd49266-d531-411b-999a-0c0d0199d949.jpg",
        "source": "iplt20.com"
      },
      {
        "src": "https://assets.bcci.tv/bcci/photos/1043/5cd49266-d531-411b-999a-0c0d0199d949.jpg",
        "source": "iplt20.com"
      }
    ],
    "paragraphs": [
      "இந்த நிலையில்தான் *தோனி* ஐபிஎல் தொடரில் இருந்து ஓய்வு பெற *போவதாக* பேச்சுக்கள் சுற்றி வரும் நிலையில்தான் சிஎஸ்கேவின் அடுத்த கேப்டன் யார் என்பது தொடர்பான ஆலோசனைகள், விவாதங்கள் எழுந்துள்ளன. இந்த நிலையில்தான் தோனி ஐபிஎல் தொடரில் இருந்து ஓய்வு பெற போவதாக பேச்சுக்கள் சுற்றி வரும் நிலையில்தான் சிஎஸ்கேவின் அடுத்த கேப்டன் யார் என்பது தொடர்பான ஆலோசனைகள், விவாதங்கள் எழுந்துள்ளன.",
      "இந்த நிலையில்தான் *தோனி* ஐபிஎல் தொடரில் இருந்து ஓய்வு பெற *போவதாக* பேச்சுக்கள் சுற்றி வரும் நிலையில்தான் சிஎஸ்கேவின் அடுத்த கேப்டன் யார் என்பது தொடர்பான ஆலோசனைகள், விவாதங்கள் எழுந்துள்ளன. இந்த நிலையில்தான் தோனி ஐபிஎல் தொடரில் இருந்து ஓய்வு பெற போவதாக பேச்சுக்கள் சுற்றி வரும் நிலையில்தான் சிஎஸ்கேவின் அடுத்த கேப்டன் யார் என்பது தொடர்பான ஆலோசனைகள், விவாதங்கள் எழுந்துள்ளன.",
      "இந்த நிலையில்தான் *தோனி* ஐபிஎல் தொடரில் இருந்து ஓய்வு பெற *போவதாக* பேச்சுக்கள் சுற்றி வரும் நிலையில்தான் சிஎஸ்கேவின் அடுத்த கேப்டன் யார் என்பது தொடர்பான ஆலோசனைகள், விவாதங்கள் எழுந்துள்ளன. இந்த நிலையில்தான் தோனி ஐபிஎல் தொடரில் இருந்து ஓய்வு பெற போவதாக பேச்சுக்கள் சுற்றி வரும் நிலையில்தான் சிஎஸ்கேவின் அடுத்த கேப்டன் யார் என்பது தொடர்பான ஆலோசனைகள், விவாதங்கள் எழுந்துள்ளன.",
      "இந்த நிலையில்தான் *தோனி* ஐபிஎல் தொடரில் இருந்து ஓய்வு பெற *போவதாக* பேச்சுக்கள் சுற்றி வரும் நிலையில்தான் சிஎஸ்கேவின் அடுத்த கேப்டன் யார் என்பது தொடர்பான ஆலோசனைகள், விவாதங்கள் எழுந்துள்ளன. இந்த நிலையில்தான் தோனி ஐபிஎல் தொடரில் இருந்து ஓய்வு பெற போவதாக பேச்சுக்கள் சுற்றி வரும் நிலையில்தான் சிஎஸ்கேவின் அடுத்த கேப்டன் யார் என்பது தொடர்பான ஆலோசனைகள், விவாதங்கள் எழுந்துள்ளன.",
      "இந்த நிலையில்தான் தோனி ஐபிஎல் தொடரில் இருந்து *ஓய்வு* பெற போவதாக பேச்சுக்கள் சுற்றி வரும் நிலையில்தான் சிஎஸ்கேவின் அடுத்த கேப்டன் யார் என்பது தொடர்பான ஆலோசனைகள், விவாதங்கள் எழுந்துள்ளன. இந்த நிலையில்தான் தோனி ஐபிஎல் தொடரில் இருந்து ஓய்வு பெற போவதாக பேச்சுக்கள் சுற்றி வரும் நிலையில்தான் சிஎஸ்கேவின் அடுத்த கேப்டன் யார் என்பது தொடர்பான ஆலோசனைகள், விவாதங்கள் எழுந்துள்ளன."
    ],
    "tags": ["ipl", "cricket", "csk", "dhoni", "2023"]
  },
  {
    "id": "i3r709r323uqewbfi",
    "title" : "This-is-a-random-title",

    "heading": "இந்த வருடம் ஓய்வு இல்லை.. ஆனால்.. கேப்டன் மாற்றம்? இதுதான் சிஎஸ்கே தோனியின் பிளான்? கேப்டன் அவரா?",
    "createdBy": "Raja",
    "createdAt": "2023-05-26T20:21:39.348Z",
    "category": "cricket",
    "bannerImage": {
      "name": "Creicket Image",
      "src": "/images/categories/cinema.jpg"
    },
    "images": [
      {
        "src": "https://assets.bcci.tv/bcci/photos/1043/842dee7a-f6b7-4e80-83ff-4fbdfe44eb11.jpg",
        "source": "iplt20.com"
      },
      {
        "src": "https://assets.bcci.tv/bcci/photos/1043/688d01fe-9efb-46ee-b346-41c954812a9a.jpg",
        "source": "iplt20.com"
      },
      {
        "src": "https://assets.bcci.tv/bcci/photos/1043/5cd49266-d531-411b-999a-0c0d0199d949.jpg",
        "source": "iplt20.com"
      },
      {
        "src": "https://assets.bcci.tv/bcci/photos/1043/5cd49266-d531-411b-999a-0c0d0199d949.jpg",
        "source": "iplt20.com"
      },
      {
        "src": "https://assets.bcci.tv/bcci/photos/1043/5cd49266-d531-411b-999a-0c0d0199d949.jpg",
        "source": "iplt20.com"
      },
      {
        "src": "https://assets.bcci.tv/bcci/photos/1043/5cd49266-d531-411b-999a-0c0d0199d949.jpg",
        "source": "iplt20.com"
      }
    ],
    "paragraphs": [
      "இந்த நிலையில்தான் *தோனி* ஐபிஎல் தொடரில் இருந்து ஓய்வு பெற *போவதாக* பேச்சுக்கள் சுற்றி வரும் நிலையில்தான் சிஎஸ்கேவின் அடுத்த கேப்டன் யார் என்பது தொடர்பான ஆலோசனைகள், விவாதங்கள் எழுந்துள்ளன. இந்த நிலையில்தான் தோனி ஐபிஎல் தொடரில் இருந்து ஓய்வு பெற போவதாக பேச்சுக்கள் சுற்றி வரும் நிலையில்தான் சிஎஸ்கேவின் அடுத்த கேப்டன் யார் என்பது தொடர்பான ஆலோசனைகள், விவாதங்கள் எழுந்துள்ளன.",
      "இந்த நிலையில்தான் *தோனி* ஐபிஎல் தொடரில் இருந்து ஓய்வு பெற *போவதாக* பேச்சுக்கள் சுற்றி வரும் நிலையில்தான் சிஎஸ்கேவின் அடுத்த கேப்டன் யார் என்பது தொடர்பான ஆலோசனைகள், விவாதங்கள் எழுந்துள்ளன. இந்த நிலையில்தான் தோனி ஐபிஎல் தொடரில் இருந்து ஓய்வு பெற போவதாக பேச்சுக்கள் சுற்றி வரும் நிலையில்தான் சிஎஸ்கேவின் அடுத்த கேப்டன் யார் என்பது தொடர்பான ஆலோசனைகள், விவாதங்கள் எழுந்துள்ளன.",
      "இந்த நிலையில்தான் *தோனி* ஐபிஎல் தொடரில் இருந்து ஓய்வு பெற *போவதாக* பேச்சுக்கள் சுற்றி வரும் நிலையில்தான் சிஎஸ்கேவின் அடுத்த கேப்டன் யார் என்பது தொடர்பான ஆலோசனைகள், விவாதங்கள் எழுந்துள்ளன. இந்த நிலையில்தான் தோனி ஐபிஎல் தொடரில் இருந்து ஓய்வு பெற போவதாக பேச்சுக்கள் சுற்றி வரும் நிலையில்தான் சிஎஸ்கேவின் அடுத்த கேப்டன் யார் என்பது தொடர்பான ஆலோசனைகள், விவாதங்கள் எழுந்துள்ளன.",
      "இந்த நிலையில்தான் *தோனி* ஐபிஎல் தொடரில் இருந்து ஓய்வு பெற *போவதாக* பேச்சுக்கள் சுற்றி வரும் நிலையில்தான் சிஎஸ்கேவின் அடுத்த கேப்டன் யார் என்பது தொடர்பான ஆலோசனைகள், விவாதங்கள் எழுந்துள்ளன. இந்த நிலையில்தான் தோனி ஐபிஎல் தொடரில் இருந்து ஓய்வு பெற போவதாக பேச்சுக்கள் சுற்றி வரும் நிலையில்தான் சிஎஸ்கேவின் அடுத்த கேப்டன் யார் என்பது தொடர்பான ஆலோசனைகள், விவாதங்கள் எழுந்துள்ளன.",
      "இந்த நிலையில்தான் தோனி ஐபிஎல் தொடரில் இருந்து *ஓய்வு* பெற போவதாக பேச்சுக்கள் சுற்றி வரும் நிலையில்தான் சிஎஸ்கேவின் அடுத்த கேப்டன் யார் என்பது தொடர்பான ஆலோசனைகள், விவாதங்கள் எழுந்துள்ளன. இந்த நிலையில்தான் தோனி ஐபிஎல் தொடரில் இருந்து ஓய்வு பெற போவதாக பேச்சுக்கள் சுற்றி வரும் நிலையில்தான் சிஎஸ்கேவின் அடுத்த கேப்டன் யார் என்பது தொடர்பான ஆலோசனைகள், விவாதங்கள் எழுந்துள்ளன."
    ],
    "tags": ["ipl", "cricket", "csk", "dhoni", "2023"]
  },
  {
    "id": "i3r709r323ubie132i",
    "title" : "new-title-for-url",
    
    "heading": "இந்த வருடம் ஓய்வு இல்லை.. ஆனால்.. கேப்டன் மாற்றம்? இதுதான் சிஎஸ்கே தோனியின் பிளான்? கேப்டன் அவரா?",
    "createdBy": "Raja",
    "createdAt": "2023-05-26T20:21:39.348Z",
    "category": "cricket",
    "bannerImage": {
      "name": "Creicket Image",
      "src": "/images/categories/random.jpg"
    },
    "images": [
      {
        "src": "https://assets.bcci.tv/bcci/photos/1043/842dee7a-f6b7-4e80-83ff-4fbdfe44eb11.jpg",
        "source": "iplt20.com"
      },
      {
        "src": "https://assets.bcci.tv/bcci/photos/1043/688d01fe-9efb-46ee-b346-41c954812a9a.jpg",
        "source": "iplt20.com"
      },
      {
        "src": "https://assets.bcci.tv/bcci/photos/1043/5cd49266-d531-411b-999a-0c0d0199d949.jpg",
        "source": "iplt20.com"
      },
      {
        "src": "https://assets.bcci.tv/bcci/photos/1043/5cd49266-d531-411b-999a-0c0d0199d949.jpg",
        "source": "iplt20.com"
      },
      {
        "src": "https://assets.bcci.tv/bcci/photos/1043/5cd49266-d531-411b-999a-0c0d0199d949.jpg",
        "source": "iplt20.com"
      },
      {
        "src": "https://assets.bcci.tv/bcci/photos/1043/5cd49266-d531-411b-999a-0c0d0199d949.jpg",
        "source": "iplt20.com"
      }
    ],
    "paragraphs": [
      "இந்த நிலையில்தான் *தோனி* ஐபிஎல் தொடரில் இருந்து ஓய்வு பெற *போவதாக* பேச்சுக்கள் சுற்றி வரும் நிலையில்தான் சிஎஸ்கேவின் அடுத்த கேப்டன் யார் என்பது தொடர்பான ஆலோசனைகள், விவாதங்கள் எழுந்துள்ளன. இந்த நிலையில்தான் தோனி ஐபிஎல் தொடரில் இருந்து ஓய்வு பெற போவதாக பேச்சுக்கள் சுற்றி வரும் நிலையில்தான் சிஎஸ்கேவின் அடுத்த கேப்டன் யார் என்பது தொடர்பான ஆலோசனைகள், விவாதங்கள் எழுந்துள்ளன.",
      "இந்த நிலையில்தான் *தோனி* ஐபிஎல் தொடரில் இருந்து ஓய்வு பெற *போவதாக* பேச்சுக்கள் சுற்றி வரும் நிலையில்தான் சிஎஸ்கேவின் அடுத்த கேப்டன் யார் என்பது தொடர்பான ஆலோசனைகள், விவாதங்கள் எழுந்துள்ளன. இந்த நிலையில்தான் தோனி ஐபிஎல் தொடரில் இருந்து ஓய்வு பெற போவதாக பேச்சுக்கள் சுற்றி வரும் நிலையில்தான் சிஎஸ்கேவின் அடுத்த கேப்டன் யார் என்பது தொடர்பான ஆலோசனைகள், விவாதங்கள் எழுந்துள்ளன.",
      "இந்த நிலையில்தான் *தோனி* ஐபிஎல் தொடரில் இருந்து ஓய்வு பெற *போவதாக* பேச்சுக்கள் சுற்றி வரும் நிலையில்தான் சிஎஸ்கேவின் அடுத்த கேப்டன் யார் என்பது தொடர்பான ஆலோசனைகள், விவாதங்கள் எழுந்துள்ளன. இந்த நிலையில்தான் தோனி ஐபிஎல் தொடரில் இருந்து ஓய்வு பெற போவதாக பேச்சுக்கள் சுற்றி வரும் நிலையில்தான் சிஎஸ்கேவின் அடுத்த கேப்டன் யார் என்பது தொடர்பான ஆலோசனைகள், விவாதங்கள் எழுந்துள்ளன.",
      "இந்த நிலையில்தான் *தோனி* ஐபிஎல் தொடரில் இருந்து ஓய்வு பெற *போவதாக* பேச்சுக்கள் சுற்றி வரும் நிலையில்தான் சிஎஸ்கேவின் அடுத்த கேப்டன் யார் என்பது தொடர்பான ஆலோசனைகள், விவாதங்கள் எழுந்துள்ளன. இந்த நிலையில்தான் தோனி ஐபிஎல் தொடரில் இருந்து ஓய்வு பெற போவதாக பேச்சுக்கள் சுற்றி வரும் நிலையில்தான் சிஎஸ்கேவின் அடுத்த கேப்டன் யார் என்பது தொடர்பான ஆலோசனைகள், விவாதங்கள் எழுந்துள்ளன.",
      "இந்த நிலையில்தான் தோனி ஐபிஎல் தொடரில் இருந்து *ஓய்வு* பெற போவதாக பேச்சுக்கள் சுற்றி வரும் நிலையில்தான் சிஎஸ்கேவின் அடுத்த கேப்டன் யார் என்பது தொடர்பான ஆலோசனைகள், விவாதங்கள் எழுந்துள்ளன. இந்த நிலையில்தான் தோனி ஐபிஎல் தொடரில் இருந்து ஓய்வு பெற போவதாக பேச்சுக்கள் சுற்றி வரும் நிலையில்தான் சிஎஸ்கேவின் அடுத்த கேப்டன் யார் என்பது தொடர்பான ஆலோசனைகள், விவாதங்கள் எழுந்துள்ளன."
    ],
    "tags": ["ipl", "cricket", "csk", "dhoni", "2023"]
  },
  {
    "id": "i3r709r323ubxxbfi",
    "title" : "my-title-for-this-news",
    "heading": "இந்த வருடம் ஓய்வு இல்லை.. ஆனால்.. கேப்டன் மாற்றம்? இதுதான் சிஎஸ்கே தோனியின் பிளான்? கேப்டன் அவரா?",
    "createdBy": "Raja",
    "createdAt": "2023-05-26T20:21:39.348Z",
    "category": "cricket",
    "bannerImage": {
      "name": "Creicket Image",
      "src": "/images/categories/trending.jpg"
    },
    "images": [
      {
        "src": "https://assets.bcci.tv/bcci/photos/1043/842dee7a-f6b7-4e80-83ff-4fbdfe44eb11.jpg",
        "source": "iplt20.com"
      },
      {
        "src": "https://assets.bcci.tv/bcci/photos/1043/688d01fe-9efb-46ee-b346-41c954812a9a.jpg",
        "source": "iplt20.com"
      },
      {
        "src": "https://assets.bcci.tv/bcci/photos/1043/5cd49266-d531-411b-999a-0c0d0199d949.jpg",
        "source": "iplt20.com"
      },
      {
        "src": "https://assets.bcci.tv/bcci/photos/1043/5cd49266-d531-411b-999a-0c0d0199d949.jpg",
        "source": "iplt20.com"
      },
      {
        "src": "https://assets.bcci.tv/bcci/photos/1043/5cd49266-d531-411b-999a-0c0d0199d949.jpg",
        "source": "iplt20.com"
      },
      {
        "src": "https://assets.bcci.tv/bcci/photos/1043/5cd49266-d531-411b-999a-0c0d0199d949.jpg",
        "source": "iplt20.com"
      }
    ],
    "paragraphs": [
      "இந்த நிலையில்தான் *தோனி* ஐபிஎல் தொடரில் இருந்து ஓய்வு பெற *போவதாக* பேச்சுக்கள் சுற்றி வரும் நிலையில்தான் சிஎஸ்கேவின் அடுத்த கேப்டன் யார் என்பது தொடர்பான ஆலோசனைகள், விவாதங்கள் எழுந்துள்ளன. இந்த நிலையில்தான் தோனி ஐபிஎல் தொடரில் இருந்து ஓய்வு பெற போவதாக பேச்சுக்கள் சுற்றி வரும் நிலையில்தான் சிஎஸ்கேவின் அடுத்த கேப்டன் யார் என்பது தொடர்பான ஆலோசனைகள், விவாதங்கள் எழுந்துள்ளன.",
      "இந்த நிலையில்தான் *தோனி* ஐபிஎல் தொடரில் இருந்து ஓய்வு பெற *போவதாக* பேச்சுக்கள் சுற்றி வரும் நிலையில்தான் சிஎஸ்கேவின் அடுத்த கேப்டன் யார் என்பது தொடர்பான ஆலோசனைகள், விவாதங்கள் எழுந்துள்ளன. இந்த நிலையில்தான் தோனி ஐபிஎல் தொடரில் இருந்து ஓய்வு பெற போவதாக பேச்சுக்கள் சுற்றி வரும் நிலையில்தான் சிஎஸ்கேவின் அடுத்த கேப்டன் யார் என்பது தொடர்பான ஆலோசனைகள், விவாதங்கள் எழுந்துள்ளன.",
      "இந்த நிலையில்தான் *தோனி* ஐபிஎல் தொடரில் இருந்து ஓய்வு பெற *போவதாக* பேச்சுக்கள் சுற்றி வரும் நிலையில்தான் சிஎஸ்கேவின் அடுத்த கேப்டன் யார் என்பது தொடர்பான ஆலோசனைகள், விவாதங்கள் எழுந்துள்ளன. இந்த நிலையில்தான் தோனி ஐபிஎல் தொடரில் இருந்து ஓய்வு பெற போவதாக பேச்சுக்கள் சுற்றி வரும் நிலையில்தான் சிஎஸ்கேவின் அடுத்த கேப்டன் யார் என்பது தொடர்பான ஆலோசனைகள், விவாதங்கள் எழுந்துள்ளன.",
      "இந்த நிலையில்தான் *தோனி* ஐபிஎல் தொடரில் இருந்து ஓய்வு பெற *போவதாக* பேச்சுக்கள் சுற்றி வரும் நிலையில்தான் சிஎஸ்கேவின் அடுத்த கேப்டன் யார் என்பது தொடர்பான ஆலோசனைகள், விவாதங்கள் எழுந்துள்ளன. இந்த நிலையில்தான் தோனி ஐபிஎல் தொடரில் இருந்து ஓய்வு பெற போவதாக பேச்சுக்கள் சுற்றி வரும் நிலையில்தான் சிஎஸ்கேவின் அடுத்த கேப்டன் யார் என்பது தொடர்பான ஆலோசனைகள், விவாதங்கள் எழுந்துள்ளன.",
      "இந்த நிலையில்தான் தோனி ஐபிஎல் தொடரில் இருந்து *ஓய்வு* பெற போவதாக பேச்சுக்கள் சுற்றி வரும் நிலையில்தான் சிஎஸ்கேவின் அடுத்த கேப்டன் யார் என்பது தொடர்பான ஆலோசனைகள், விவாதங்கள் எழுந்துள்ளன. இந்த நிலையில்தான் தோனி ஐபிஎல் தொடரில் இருந்து ஓய்வு பெற போவதாக பேச்சுக்கள் சுற்றி வரும் நிலையில்தான் சிஎஸ்கேவின் அடுத்த கேப்டன் யார் என்பது தொடர்பான ஆலோசனைகள், விவாதங்கள் எழுந்துள்ளன."
    ],
    "tags": ["ipl", "cricket", "csk", "dhoni", "2023"]
  }
]
